{
    "platforms": [
        [
            0,
            560,
            800,
            40
        ],
        [
            140,
            500,
            100,
            20
        ],
        [
            340,
            440,
            100,
            20
        ],
        [
            540,
            380,
            100,
            20
        ],
        [
            740,
            320,
            60,
            20
        ]
    ],
    "player_start": [
        130,
        520
    ],
    "exit": [
        780,
        260,
        40,
        60
    ],
    "button": [
        760,
        300,
        40,
        20
    ],
    "door": [
        780,
        260,
        40,
        60
    ],
    "moving_platform": {
        "rect": [
            450,
            540,
            100,
            20
        ],
        "x1": 450,
        "x2": 740,
        "speed": 2
    }
}